[
  {
    "postalCode": "0691336",
    "regionId": 1,
    "region": "北海道",
    "locality": "夕張郡長沼町",
    "address1": "川沿",
    "address2": "",
    "regionKana": "ホッカイドウ",
    "localityKana": "ユウバリグンナガヌマチョウ",
    "address1Kana": "カワゾイ",
    "address2Kana": ""
  },
  {
    "postalCode": "0691336",
    "regionId": 1,
    "region": "北海道",
    "locality": "夕張郡長沼町",
    "address1": "栄町",
    "address2": "",
    "regionKana": "ホッカイドウ",
    "localityKana": "ユウバリグンナガヌマチョウ",
    "address1Kana": "サカエマチ",
    "address2Kana": ""
  }
]