[
  {
    "postalCode": "0393177",
    "regionId": 2,
    "region": "青森県",
    "locality": "上北郡野辺地町",
    "address1": "柴崎",
    "address2": "",
    "regionKana": "アオモリケン",
    "localityKana": "カミキタグンノヘジマチ",
    "address1Kana": "シバサキ",
    "address2Kana": ""
  },
  {
    "postalCode": "0393177",
    "regionId": 2,
    "region": "青森県",
    "locality": "上北郡野辺地町",
    "address1": "八ノ木谷地",
    "address2": "",
    "regionKana": "アオモリケン",
    "localityKana": "カミキタグンノヘジマチ",
    "address1Kana": "ハノキヤチ",
    "address2Kana": ""
  }
]